setup.cfg
setup.py
powerkube/__init__.py
powerkube.egg-info/PKG-INFO
powerkube.egg-info/SOURCES.txt
powerkube.egg-info/dependency_links.txt
powerkube.egg-info/requires.txt
powerkube.egg-info/top_level.txt