Metadata-Version: 1.1
Name: powerkube
Version: 0.1.3
Summary: A powerline segment to show kubernetes context items, with toggling and alert color functionality
Home-page: https://github.com/zcmarine/powerkube
Author: Zach Marine
Author-email: zcmarine@gmail.com
License: Copyright
Download-URL: https://github.com/zcmarine/powerkube/tarball/0.1.3
Keywords: powerline kubernetes k8s context segment
Platform: UNKNOWN
Classifier: Programming Language :: Python :: 2.7
Classifier: Programming Language :: Python :: 2 :: Only
Classifier: Environment :: Console
Classifier: Intended Audience :: Developers
Classifier: License :: OSI Approved :: Apache Software License
Classifier: Topic :: Terminals
